allennlp_wordsplitter_ltp/__init__.py
allennlp_wordsplitter_ltp/_version.py
allennlp_wordsplitter_ltp/version.py
allennlp_wordsplitter_ltp/wordspliters.py
allennlp_wordsplitter_ltp-0.1a1.dist-info/AUTHORS.md
allennlp_wordsplitter_ltp-0.1a1.dist-info/METADATA
allennlp_wordsplitter_ltp-0.1a1.dist-info/WHEEL
allennlp_wordsplitter_ltp-0.1a1.dist-info/namespace_packages.txt
allennlp_wordsplitter_ltp-0.1a1.dist-info/top_level.txt
allennlp_wordsplitter_ltp-0.1a1.dist-info/RECORD
