Metadata-Version: 2.1
Name: allennlp-wordsplitter-ltp
Version: 0.1a1
Summary: LTP word splitter for AllenNLP
Home-page: https://github.com/tanbro/allennlp_wordsplitter_ltp
Author: liu xue yan
Author-email: liu_xue_yan@foxmail.com
License: UNKNOWN
Platform: UNKNOWN
Requires-Dist: allennlp (<0.9,>=0.7)
Requires-Dist: requests
Requires-Dist: overrides
Provides-Extra: ltp
Requires-Dist: pyltp ; extra == 'ltp'
